[ZONE CORE:HTMLHEAD]
<style>
DIV { color : black;
	text-align:left;
	border-style : inset;
	border-color : [CORE_FGCOLOR];
	border-width: 1pt;
  background-color: [CORE_BGCOLORALTERN];
	padding : 3pt;		
}
</style>
<script language="JavaScript">
function changeFormat(fmt) {
    switch(fmt) {
      case 'vcard':
          document.getElementById('fsend').action='[CORE_STANDURL]&app=[APPNAME]&action=USERCARD_IMPORTVCARD';
          document.getElementById('bsubmit').value='[TEXT:Import vcard]';
          document.getElementById('dcsv').style.display='none';
          document.getElementById('dvcard').style.display='block';
       break;
      case 'csv':
	document.location.href='[CORE_STANDURL]&app=GENERIC&action=GENERIC_EDITIMPORT&famid=120';
	return;
          document.getElementById('fsend').action='[CORE_STANDURL]&app=[APPNAME]&action=GENERIC_IMPORTCSV';
          document.getElementById('bsubmit').value='[TEXT:Import CSV]';
          document.getElementById('dvcard').style.display='none';
          document.getElementById('dcsv').style.display='block';
       break;
    }
}

</script>






<H2 id="title">[TEXT:Import from]

<select style="font-size:18pt" name="saction" onchange="changeFormat(this.options[this.selectedIndex].value)">
    <option  value="vcard">[TEXT:VCARD]</option>
    <option  value="csv">[TEXT:CSV]</option>
</select>


</H2>

<FORM ENCTYPE="multipart/form-data" id="fsend" name="fsend" action="[CORE_STANDURL]&app=[APPNAME]&action=USERCARD_IMPORTVCARD" method="post" >




<INPUT NAME="vcardfile" SIZE=48 TYPE="file" accept="text/x-vcard,text/*.csv" VALUE=""><HR>
<label for="category"> [TEXT:category]:</label><BR>


    
[BLOCK CATG]
    <input type="checkbox" name="category[]" VALUE="[id]" style="margin:0px [level]px 0px 0px">[title]</input><BR>
[ENDBLOCK CATG]

<BR>
<label for="visibility"> [TEXT:visibility]&nbsp;:</label>
 <select name="privacity" >
    <option value="P" >[TEXT:private card]</option>
    <option value="R" selected>[TEXT:public card - read access]</option>
    <option value="W" >[TEXT:public card - write access]</option>
  </select>

<BR>
<label for="policy"> [TEXT:policy if same title]&nbsp;:</label>
  <SELECT NAME="policy">
            <OPTION VALUE="add">[TEXT:Add new card (duplicate title)]</OPTION>
            <OPTION VALUE="update">[TEXT:Replace address book card if has permission else duplicate]</OPTION>
            <OPTION VALUE="keep">[TEXT:Keep address book card]</OPTION>
  </SELECT><BR>
<input type="submit" id="bsubmit" value="[TEXT:Import vcard]">
 <input type="button" value=[TEXT:Help] onClick="subwindow([FDL_VD2SIZE],[FDL_HD2SIZE],'helpwhat','[CORE_STANDURL]app=CORE&action=HELPVIEW&appname=USERCARD&sectid=usercard.adm.import');"> 
</FORM>
<hr width="50%">
<div  id="dvcard">
<p>[TEXT:Vcard example]</p>
<pre width="40">
BEGIN:VCARD
FN:Martin Jean
N:Martin;Jean
N;GIVEN:Jean
N;FAMILY:Martin
URL:www.anakeen.com
URL;WORK:www.anakeen.com
ORG:Anakeen
ORG;NAME:Anakeen
EMAIL;INTERNET:jean.martin@free.fr
ADR;WORK:;;21 rue Clément Ader\nCedex 9;Colomiers;;31700
TEL;WORK:0565653563
TEL;FAX:0565650000
TEL;CELL:0665653566
END:VCARD
</pre>
</div>

<div  style="display:none" id="dcsv">
<p>[TEXT:CSV specification file]</p>
<p>[TEXT:The separator field is the semicolon(;)]. 
[TEXT:The first four fields must not be change, they identified the card structure]. 
[TEXT:Only one line by personn is authorized]. 
[TEXT:If an attribut is a multiline string, use the \ n characters to specify the new line]</p>
<p style="font-family:courier">[format]</p>
</div>
[ZONE CORE:HTMLFOOT]


