[BLOCK FRAME]

<tr >
  <td  colspan="2" >
      <fieldset id="F[frameid]" class="frame" opened="true">
          <legend style="cursor:pointer">
            <span class="dyp-frame-opener" onclick="viewornot('T[frameid]', ['F[frameid]'])">[flabel]</span>
            [IF ehelp]
            <span title="[TEXT:Online help]" class="dyp-help-hint" onclick="subwindow([FDL_VD2SIZE],[FDL_HD2SIZE],'help[ehelpid]','[ehelp]')"></span>
            [ENDIF ehelp]
          </legend>
<table width="100%" id="T[frameid]" opened="true">
[BLOCK FVALUES]
<tr class="FREEDOMBack1">
            [IFNOT TESTARRAY]
  <td width="30%" valign="top" class="[labelclass]">
[IF aehelp][alabel]<a style="cursor:help" onclick="subwindow([FDL_VD2SIZE],[FDL_HD2SIZE],'help[aehelpid]','[aehelp]')"><span title="[TEXT:Online help]" class="dyp-help-hint"></span></a>[ENDIF aehelp]
[IFNOT aehelp][alabel][ENDIF aehelp]&nbsp;:&nbsp;</td>
  <td  >[avalue]</td>
            [ENDIF TESTARRAY]
            [IF TESTARRAY]
  <td colspan="3">[IF viewlabel]<span class="[labelclass]">
[IF aehelp][alabel]<a style="cursor:help" onclick="subwindow([FDL_VD2SIZE],[FDL_HD2SIZE],'help[aehelpid]','[aehelp]')"><span title="[TEXT:Online help]" class="dyp-help-hint"></span></a>[ENDIF aehelp]
[IFNOT aehelp][alabel][ENDIF aehelp]&nbsp;:&nbsp;</span><br>[ENDIF viewlabel][avalue]</td>
            [ENDIF TESTARRAY]
</tr>
[ENDBLOCK FVALUES]
</table>

</fieldset>
</td></tr>

<tr style="display:none"><td>
[BLOCK FHIDDENS]
[avalue]
[ENDBLOCK FHIDDENS]
</td></tr>

[ENDBLOCK FRAME]
