[IF caption]<fieldset >
    <legend style="cursor:pointer" onclick="viewornot('T[attrid]')">
        [caption]
    </legend>[ENDIF caption]
    <table border=1
           cellspacing="0"
           id="T[attrid]" 
           class="tarray[IFNOT caption] border[ENDIF caption]"
           style="width:[tableWidth];[tableStyle]">
        <thead>
            <tr>
                [IFNOT readonly]<th class="tools"/>[ENDIF readonly]
                [BLOCK TATTR]<th colspan="[thspan]"
                    style="[IF elabel]cursor:help;[ENDIF elabel][astyle]"
                    [IF elabel]title="[elabel]"[ENDIF elabel]
                    class="[ahclass][IF elabel] withElabel[ENDIF elabel]">
                    [alabel]
                </th>[ENDBLOCK TATTR]
                [IFNOT ISIE][IF tableheight]
<th style="width:20px;visibility:hidden"/>[ENDIF tableheight][ENDIF ISIE]
            </tr>
        </thead>
        <tbody id="tbody[attrid]" [IFNOT ISIE][IF tableheight]style="height:[tableheight];overflow:auto"[ENDIF tableheight][ENDIF ISIE]>
            [BLOCK EATTR]<tr index="[index]" onmouseover="droptr(event);">
                [IFNOT readonly]<td class="tools" align="left">
                    <div class="drag-button" title="[TEXT:drag to move]" onmousedown="adrag(event,this);return false;">&nbsp;&nbsp;</div>
                    <input class="button select-button" name="sel[attrid]" type="radio" title="[TEXT:Select. Use ctrl-&uarr; &darr; to up/down selection]" onmousedown="selecttr(this,this.parentNode.parentNode);">
                    <input class="button trash-button" type="button" name="trash" style="visibility:hidden" title="[TEXT:delete selected]" onclick="delseltr()">
                </td>[ENDIF readonly]
                [BLOCK [bevalue]]<td class="[eiclass]" attrid="[cellattrid]" type="[cellatype]" multiple="[cellmultiple]" style="width:[vhw];background-color:[bgcolor];[tdstyle]">
                    [eivalue]
                </td>[ENDBLOCK [bevalue]]
            </tr>[ENDBLOCK EATTR]
            [IFNOT readonly]<tr id="lasttr[attrid]" onmouseover="droptr(event);">
                <td class="und tools" align="right">
                    [IF useadd]<input class="button unselect-button" type="button" name="unselect" style="visibility:hidden" title="[TEXT:unselect]" align="bottom" onclick="unseltr()">[ENDIF useadd]
                    <input class="button duplicate-button" type="button" name="unselect" style="visibility:hidden" title="[TEXT:duplicate]" onclick="duptr();return false;">
                </td>
                <td colspan="[footspan]">
                    [IF useadd]<input class="button add-button" type="button" id="tiadd[attrid]" title="[TEXT:add]" onclick="addtr('tnew[attrid]','tbody[attrid]');return false;">[ENDIF useadd]
                    [IF addfunc]<input class="normal [attrid]" type="button" id="tispecial[attrid]" title="[addtitle]" value="[addsymbol]" onclick="[addfunc];return false;">[ENDIF addfunc]
                </td>
            </tr>[ENDIF readonly] 
        </tbody>
        <tfoot>
            <tr style="display:none;" onmouseover="droptr(event);" id="tnew[attrid]">
                <td class="tools" align="left">
                    <div class="drag-button" title="[TEXT:drag to move]" onmousedown="adrag(event,this);">&nbsp;&nbsp;</div>
                    <input class="button select-button" name="sel[attrid]" type="radio" title="[TEXT:Select. Use ctrl-&uarr; &darr; to up/down selection]" onmousedown="selecttr(this,this.parentNode.parentNode);">
                     <input class="button trash-button" type="button" name="trash" style="visibility:hidden" title="[TEXT:delete selected]" onclick="delseltr()">
                </td>
                [BLOCK IATTR]<td class="[ihclass]" attrid="[cellattrid]" type="[cellatype]" multiple="[cellmultiple]" style="background-color:[bgcolor];width:[ihw];[tdstyle]">
                    [ilabel]
                </td>[ENDBLOCK IATTR]
            </tr>
        </tfoot>
    </table>
[IF caption]</fieldset>[ENDIF caption]